imandrax_api_models/__init__.py
imandrax_api_models/client.py
imandrax_api_models/context_utils.py
imandrax_api_models/logging_utils.py
imandrax_api_models/proto_models/__init__.py
imandrax_api_models/proto_models/artmsg.py
imandrax_api_models/proto_models/error.py
imandrax_api_models/proto_models/locs.py
imandrax_api_models/proto_models/session.py
imandrax_api_models/proto_models/simple_api.py
imandrax_api_models/proto_models/task.py
imandrax_api_models/proto_models/utils.py
imandrax_api_models/proto_utils.py
imandrax_api_models/py.typed
imandrax_api_models/yaml_utils.py
imandrax_api_models-18.0.0.dist-info/WHEEL
imandrax_api_models-18.0.0.dist-info/entry_points.txt
imandrax_api_models-18.0.0.dist-info/METADATA
imandrax_api_models-18.0.0.dist-info/RECORD
